{"src/lib/components/Mviewer.react.js":{"description":"","displayName":"Mviewer","methods":[],"props":{"id":{"type":{"name":"string"},"required":false,"description":"The ID used to identify this component in Dash callbacks."},"img":{"type":{"name":"string"},"required":true,"description":"Main image."},"imgWidth":{"type":{"name":"number"},"required":true,"description":"Main image width."},"imgHeight":{"type":{"name":"number"},"required":true,"description":"Main image height."},"inset":{"type":{"name":"string"},"required":true,"description":"Inset image (to show region of main image)\ncurrently being displayed."},"insetWidth":{"type":{"name":"number"},"required":true,"description":"Inset image width."},"insetHeight":{"type":{"name":"number"},"required":true,"description":"Inset image height."},"width":{"type":{"name":"number"},"required":false,"description":"App window width."},"height":{"type":{"name":"number"},"required":false,"description":"App window height."},"cutoutDesc":{"type":{"name":"string"},"required":false,"description":"Command string."},"zoombox":{"type":{"name":"shape","value":{"zoom":{"name":"number","required":true},"width":{"name":"number","required":true},"height":{"name":"number","required":true},"xmin":{"name":"number","required":true},"ymin":{"name":"number","required":true},"dx":{"name":"number","required":true},"dy":{"name":"number","required":true}}},"required":false,"description":"Visible window box and zoom factor."},"box":{"type":{"name":"shape","value":{"xmin":{"name":"number","required":true},"ymin":{"name":"number","required":true},"dx":{"name":"number","required":true},"dy":{"name":"number","required":true},"screenXmin":{"name":"number","required":true},"screenYmin":{"name":"number","required":true},"screenDx":{"name":"number","required":true},"screenDy":{"name":"number","required":true}}},"required":false,"description":"Box region selected (returned)."},"pick":{"type":{"name":"shape","value":{"x":{"name":"number","required":true},"y":{"name":"number","required":true}}},"required":false,"description":"Location of a location pick (returned)."},"cmdStr":{"type":{"name":"string"},"required":false,"description":"Command string (returned)."},"setProps":{"type":{"name":"func"},"required":false,"description":"Dash-assigned callback that should be called to report property changes\nto Dash, to make them available for callbacks."}}}}